{"title":"terry","author":"JamesM","link":"","permaLinks":[],"format":"markdown","content":"\nThis is my story about terry\n\n> It is using [markdown](https://github.com/adam-p/markdown-here/wiki/Markdown-Cheatsheet)\n\n# Yes, that’s correct","errors":[],"publicId":"terry","html":"<p>This is my story about terry</p>\n<blockquote>\n<p>It is using <a href=\"https://github.com/adam-p/markdown-here/wiki/Markdown-Cheatsheet\">markdown</a></p>\n</blockquote>\n<h1 id=\"yes-that-s-correct\">Yes, that’s correct</h1>\n","id":"gan3u3wu4jnjat32d"}